[
    {
        "count": 294,
        "SUMMONS_DATE": "06/2019",
        "BORO": "BROOKLYN",
        "JURISDICTION_CODE": "0",
        "AGE_GROUP": "25-44",
        "SEX": "M",
        "RACE": "BLACK"
    },
    {
        "count": 21,
        "SUMMONS_DATE": "06/2019",
        "BORO": "BROOKLYN",
        "JURISDICTION_CODE": "0",
        "AGE_GROUP": "25-44",
        "SEX": "M",
        "RACE": "BLACK HISPANIC"
    },
    {
        "count": 79,
        "SUMMONS_DATE": "06/2019",
        "BORO": "QUEENS",
        "JURISDICTION_CODE": "0",
        "AGE_GROUP": "45-64",
        "SEX": "M",
        "RACE": "BLACK"
    },
    {
        "count": 836,
        "SUMMONS_DATE": "06/2019",
        "BORO": "QUEENS",
        "JURISDICTION_CODE": "0",
        "AGE_GROUP": "UNKNOWN",
        "SEX": "",
        "RACE": ""
    },
    {
        "count": 59,
        "SUMMONS_DATE": "06/2019",
        "BORO": "NEW YORK",
        "JURISDICTION_CODE": "0",
        "AGE_GROUP": "25-44",
        "SEX": "M",
        "RACE": "WHITE HISPANIC"
    },
    {
        "count": 70,
        "SUMMONS_DATE": "06/2019",
        "BORO": "QUEENS",
        "JURISDICTION_CODE": "0",
        "AGE_GROUP": "25-44",
        "SEX": "M",
        "RACE": "WHITE HISPANIC"
    },
    {
        "count": 301,
        "SUMMONS_DATE": "06/2019",
        "BORO": "BRONX",
        "JURISDICTION_CODE": "0",
        "AGE_GROUP": "UNKNOWN",
        "SEX": "",
        "RACE": ""
    },
    {
        "count": 56,
        "SUMMONS_DATE": "06/2019",
        "BORO": "QUEENS",
        "JURISDICTION_CODE": "0",
        "AGE_GROUP": "18-24",
        "SEX": "M",
        "RACE": "BLACK"
    },
    {
        "count": 19,
        "SUMMONS_DATE": "06/2019",
        "BORO": "NEW YORK",
        "JURISDICTION_CODE": "0",
        "AGE_GROUP": "25-44",
        "SEX": "F",
        "RACE": "BLACK"
    },
    {
        "count": 150,
        "SUMMONS_DATE": "06/2019",
        "BORO": "BRONX",
        "JURISDICTION_CODE": "0",
        "AGE_GROUP": "25-44",
        "SEX": "M",
        "RACE": "WHITE HISPANIC"
    },
    {
        "count": 114,
        "SUMMONS_DATE": "06/2019",
        "BORO": "BRONX",
        "JURISDICTION_CODE": "0",
        "AGE_GROUP": "25-44",
        "SEX": "M",
        "RACE": "BLACK HISPANIC"
    },
    {
        "count": 10,
        "SUMMONS_DATE": "06/2019",
        "BORO": "STATEN ISLAND",
        "JURISDICTION_CODE": "0",
        "AGE_GROUP": "45-64",
        "SEX": "M",
        "RACE": "WHITE"
    },
    {
        "count": 33,
        "SUMMONS_DATE": "06/2019",
        "BORO": "NEW YORK",
        "JURISDICTION_CODE": "1",
        "AGE_GROUP": "25-44",
        "SEX": "M",
        "RACE": "BLACK"
    },
    {
        "count": 2,
        "SUMMONS_DATE": "06/2019",
        "BORO": "QUEENS",
        "JURISDICTION_CODE": "0",
        "AGE_GROUP": "65+",
        "SEX": "F",
        "RACE": "WHITE HISPANIC"
    },
    {
        "count": 135,
        "SUMMONS_DATE": "06/2019",
        "BORO": "QUEENS",
        "JURISDICTION_CODE": "0",
        "AGE_GROUP": "25-44",
        "SEX": "M",
        "RACE": "BLACK"
    },
    {
        "count": 35,
        "SUMMONS_DATE": "06/2019",
        "BORO": "STATEN ISLAND",
        "JURISDICTION_CODE": "0",
        "AGE_GROUP": "25-44",
        "SEX": "M",
        "RACE": "BLACK"
    },
    {
        "count": 1,
        "SUMMONS_DATE": "06/2019",
        "BORO": "NEW YORK",
        "JURISDICTION_CODE": "2",
        "AGE_GROUP": "<18",
        "SEX": "M",
        "RACE": "AMERICAN INDIAN/ALASKAN NATIVE"
    },
    {
        "count": 188,
        "SUMMONS_DATE": "06/2019",
        "BORO": "BROOKLYN",
        "JURISDICTION_CODE": "0",
        "AGE_GROUP": "18-24",
        "SEX": "M",
        "RACE": "BLACK"
    },
    {
        "count": 172,
        "SUMMONS_DATE": "06/2019",
        "BORO": "BRONX",
        "JURISDICTION_CODE": "0",
        "AGE_GROUP": "25-44",
        "SEX": "M",
        "RACE": "BLACK"
    },
    {
        "count": 42,
        "SUMMONS_DATE": "06/2019",
        "BORO": "BRONX",
        "JURISDICTION_CODE": "1",
        "AGE_GROUP": "25-44",
        "SEX": "M",
        "RACE": "BLACK"
    },
    {
        "count": 9,
        "SUMMONS_DATE": "06/2019",
        "BORO": "BROOKLYN",
        "JURISDICTION_CODE": "0",
        "AGE_GROUP": "18-24",
        "SEX": "F",
        "RACE": "WHITE"
    },
    {
        "count": 106,
        "SUMMONS_DATE": "06/2019",
        "BORO": "NEW YORK",
        "JURISDICTION_CODE": "0",
        "AGE_GROUP": "25-44",
        "SEX": "M",
        "RACE": "BLACK"
    },
    {
        "count": 59,
        "SUMMONS_DATE": "06/2019",
        "BORO": "NEW YORK",
        "JURISDICTION_CODE": "0",
        "AGE_GROUP": "25-44",
        "SEX": "M",
        "RACE": "WHITE"
    },
    {
        "count": 6,
        "SUMMONS_DATE": "06/2019",
        "BORO": "QUEENS",
        "JURISDICTION_CODE": "0",
        "AGE_GROUP": "45-64",
        "SEX": "F",
        "RACE": "WHITE HISPANIC"
    },
    {
        "count": 111,
        "SUMMONS_DATE": "06/2019",
        "BORO": "BROOKLYN",
        "JURISDICTION_CODE": "0",
        "AGE_GROUP": "45-64",
        "SEX": "M",
        "RACE": "BLACK"
    },
    {
        "count": 1,
        "SUMMONS_DATE": "06/2019",
        "BORO": "BROOKLYN",
        "JURISDICTION_CODE": "1",
        "AGE_GROUP": "<18",
        "SEX": "M",
        "RACE": "WHITE HISPANIC"
    },
    {
        "count": 45,
        "SUMMONS_DATE": "06/2019",
        "BORO": "BROOKLYN",
        "JURISDICTION_CODE": "0",
        "AGE_GROUP": "<18",
        "SEX": "M",
        "RACE": "BLACK"
    },
    {
        "count": 8,
        "SUMMONS_DATE": "06/2019",
        "BORO": "NEW YORK",
        "JURISDICTION_CODE": "0",
        "AGE_GROUP": "18-24",
        "SEX": "F",
        "RACE": "WHITE"
    },
    {
        "count": 16,
        "SUMMONS_DATE": "06/2019",
        "BORO": "QUEENS",
        "JURISDICTION_CODE": "0",
        "AGE_GROUP": "18-24",
        "SEX": "M",
        "RACE": "ASIAN / PACIFIC ISLANDER"
    },
    {
        "count": 22,
        "SUMMONS_DATE": "06/2019",
        "BORO": "BRONX",
        "JURISDICTION_CODE": "2",
        "AGE_GROUP": "25-44",
        "SEX": "M",
        "RACE": "WHITE HISPANIC"
    },
    {
        "count": 29,
        "SUMMONS_DATE": "06/2019",
        "BORO": "NEW YORK",
        "JURISDICTION_CODE": "0",
        "AGE_GROUP": "18-24",
        "SEX": "M",
        "RACE": "WHITE HISPANIC"
    },
    {
        "count": 27,
        "SUMMONS_DATE": "06/2019",
        "BORO": "QUEENS",
        "JURISDICTION_CODE": "0",
        "AGE_GROUP": "18-24",
        "SEX": "M",
        "RACE": "WHITE HISPANIC"
    },
    {
        "count": 51,
        "SUMMONS_DATE": "06/2019",
        "BORO": "BROOKLYN",
        "JURISDICTION_CODE": "2",
        "AGE_GROUP": "25-44",
        "SEX": "M",
        "RACE": "BLACK"
    },
    {
        "count": 32,
        "SUMMONS_DATE": "06/2019",
        "BORO": "BROOKLYN",
        "JURISDICTION_CODE": "0",
        "AGE_GROUP": "45-64",
        "SEX": "M",
        "RACE": "WHITE HISPANIC"
    },
    {
        "count": 3,
        "SUMMONS_DATE": "06/2019",
        "BORO": "NEW YORK",
        "JURISDICTION_CODE": "0",
        "AGE_GROUP": "65+",
        "SEX": "M",
        "RACE": "BLACK"
    },
    {
        "count": 62,
        "SUMMONS_DATE": "06/2019",
        "BORO": "BRONX",
        "JURISDICTION_CODE": "0",
        "AGE_GROUP": "45-64",
        "SEX": "M",
        "RACE": "BLACK"
    },
    {
        "count": 49,
        "SUMMONS_DATE": "06/2019",
        "BORO": "BROOKLYN",
        "JURISDICTION_CODE": "0",
        "AGE_GROUP": "25-44",
        "SEX": "F",
        "RACE": "BLACK"
    },
    {
        "count": 60,
        "SUMMONS_DATE": "06/2019",
        "BORO": "NEW YORK",
        "JURISDICTION_CODE": "0",
        "AGE_GROUP": "45-64",
        "SEX": "M",
        "RACE": "BLACK"
    },
    {
        "count": 9,
        "SUMMONS_DATE": "06/2019",
        "BORO": "BROOKLYN",
        "JURISDICTION_CODE": "0",
        "AGE_GROUP": "<18",
        "SEX": "M",
        "RACE": "WHITE HISPANIC"
    },
    {
        "count": 14,
        "SUMMONS_DATE": "06/2019",
        "BORO": "STATEN ISLAND",
        "JURISDICTION_CODE": "0",
        "AGE_GROUP": "45-64",
        "SEX": "M",
        "RACE": "BLACK"
    },
    {
        "count": 4,
        "SUMMONS_DATE": "06/2019",
        "BORO": "NEW YORK",
        "JURISDICTION_CODE": "0",
        "AGE_GROUP": "45-64",
        "SEX": "M",
        "RACE": "BLACK HISPANIC"
    },
    {
        "count": 5,
        "SUMMONS_DATE": "06/2019",
        "BORO": "NEW YORK",
        "JURISDICTION_CODE": "2",
        "AGE_GROUP": "18-24",
        "SEX": "M",
        "RACE": "WHITE HISPANIC"
    },
    {
        "count": 5,
        "SUMMONS_DATE": "06/2019",
        "BORO": "NEW YORK",
        "JURISDICTION_CODE": "0",
        "AGE_GROUP": "45-64",
        "SEX": "F",
        "RACE": "WHITE"
    },
    {
        "count": 37,
        "SUMMONS_DATE": "06/2019",
        "BORO": "QUEENS",
        "JURISDICTION_CODE": "0",
        "AGE_GROUP": "25-44",
        "SEX": "M",
        "RACE": "ASIAN / PACIFIC ISLANDER"
    },
    {
        "count": 22,
        "SUMMONS_DATE": "06/2019",
        "BORO": "BROOKLYN",
        "JURISDICTION_CODE": "0",
        "AGE_GROUP": "18-24",
        "SEX": "M",
        "RACE": "WHITE"
    },
    {
        "count": 75,
        "SUMMONS_DATE": "06/2019",
        "BORO": "BROOKLYN",
        "JURISDICTION_CODE": "0",
        "AGE_GROUP": "25-44",
        "SEX": "M",
        "RACE": "WHITE HISPANIC"
    },
    {
        "count": 46,
        "SUMMONS_DATE": "06/2019",
        "BORO": "BROOKLYN",
        "JURISDICTION_CODE": "0",
        "AGE_GROUP": "25-44",
        "SEX": "M",
        "RACE": "WHITE"
    },
    {
        "count": 20,
        "SUMMONS_DATE": "06/2019",
        "BORO": "BRONX",
        "JURISDICTION_CODE": "0",
        "AGE_GROUP": "18-24",
        "SEX": "F",
        "RACE": "WHITE HISPANIC"
    },
    {
        "count": 119,
        "SUMMONS_DATE": "06/2019",
        "BORO": "BRONX",
        "JURISDICTION_CODE": "0",
        "AGE_GROUP": "18-24",
        "SEX": "M",
        "RACE": "WHITE HISPANIC"
    },
    {
        "count": 15,
        "SUMMONS_DATE": "06/2019",
        "BORO": "STATEN ISLAND",
        "JURISDICTION_CODE": "0",
        "AGE_GROUP": "25-44",
        "SEX": "M",
        "RACE": "WHITE HISPANIC"
    },
    {
        "count": 8,
        "SUMMONS_DATE": "06/2019",
        "BORO": "QUEENS",
        "JURISDICTION_CODE": "0",
        "AGE_GROUP": "45-64",
        "SEX": "F",
        "RACE": "BLACK"
    },
    {
        "count": 41,
        "SUMMONS_DATE": "06/2019",
        "BORO": "BROOKLYN",
        "JURISDICTION_CODE": "2",
        "AGE_GROUP": "18-24",
        "SEX": "M",
        "RACE": "BLACK"
    },
    {
        "count": 10,
        "SUMMONS_DATE": "06/2019",
        "BORO": "QUEENS",
        "JURISDICTION_CODE": "0",
        "AGE_GROUP": "25-44",
        "SEX": "F",
        "RACE": "ASIAN / PACIFIC ISLANDER"
    },
    {
        "count": 22,
        "SUMMONS_DATE": "06/2019",
        "BORO": "STATEN ISLAND",
        "JURISDICTION_CODE": "0",
        "AGE_GROUP": "18-24",
        "SEX": "M",
        "RACE": "BLACK"
    },
    {
        "count": 4,
        "SUMMONS_DATE": "06/2019",
        "BORO": "BRONX",
        "JURISDICTION_CODE": "0",
        "AGE_GROUP": "<18",
        "SEX": "F",
        "RACE": "BLACK HISPANIC"
    },
    {
        "count": 28,
        "SUMMONS_DATE": "06/2019",
        "BORO": "NEW YORK",
        "JURISDICTION_CODE": "1",
        "AGE_GROUP": "45-64",
        "SEX": "M",
        "RACE": "BLACK"
    },
    {
        "count": 3,
        "SUMMONS_DATE": "06/2019",
        "BORO": "BROOKLYN",
        "JURISDICTION_CODE": "0",
        "AGE_GROUP": "18-24",
        "SEX": "F",
        "RACE": "ASIAN / PACIFIC ISLANDER"
    },
    {
        "count": 3,
        "SUMMONS_DATE": "06/2019",
        "BORO": "BROOKLYN",
        "JURISDICTION_CODE": "0",
        "AGE_GROUP": "<18",
        "SEX": "M",
        "RACE": "BLACK HISPANIC"
    },
    {
        "count": 23,
        "SUMMONS_DATE": "06/2019",
        "BORO": "NEW YORK",
        "JURISDICTION_CODE": "0",
        "AGE_GROUP": "18-24",
        "SEX": "M",
        "RACE": "WHITE"
    },
    {
        "count": 85,
        "SUMMONS_DATE": "06/2019",
        "BORO": "BRONX",
        "JURISDICTION_CODE": "0",
        "AGE_GROUP": "18-24",
        "SEX": "M",
        "RACE": "BLACK HISPANIC"
    },
    {
        "count": 5,
        "SUMMONS_DATE": "06/2019",
        "BORO": "NEW YORK",
        "JURISDICTION_CODE": "0",
        "AGE_GROUP": "25-44",
        "SEX": "M",
        "RACE": "AMERICAN INDIAN/ALASKAN NATIVE"
    },
    {
        "count": 25,
        "SUMMONS_DATE": "06/2019",
        "BORO": "BROOKLYN",
        "JURISDICTION_CODE": "0",
        "AGE_GROUP": "25-44",
        "SEX": "M",
        "RACE": "ASIAN / PACIFIC ISLANDER"
    },
    {
        "count": 2,
        "SUMMONS_DATE": "06/2019",
        "BORO": "NEW YORK",
        "JURISDICTION_CODE": "2",
        "AGE_GROUP": "<18",
        "SEX": "F",
        "RACE": "BLACK"
    },
    {
        "count": 14,
        "SUMMONS_DATE": "06/2019",
        "BORO": "BROOKLYN",
        "JURISDICTION_CODE": "2",
        "AGE_GROUP": "18-24",
        "SEX": "M",
        "RACE": "WHITE HISPANIC"
    },
    {
        "count": 11,
        "SUMMONS_DATE": "06/2019",
        "BORO": "QUEENS",
        "JURISDICTION_CODE": "0",
        "AGE_GROUP": "25-44",
        "SEX": "F",
        "RACE": "WHITE HISPANIC"
    },
    {
        "count": 20,
        "SUMMONS_DATE": "06/2019",
        "BORO": "BRONX",
        "JURISDICTION_CODE": "0",
        "AGE_GROUP": "<18",
        "SEX": "M",
        "RACE": "BLACK"
    },
    {
        "count": 1,
        "SUMMONS_DATE": "06/2019",
        "BORO": "STATEN ISLAND",
        "JURISDICTION_CODE": "0",
        "AGE_GROUP": "45-64",
        "SEX": "F",
        "RACE": "WHITE"
    },
    {
        "count": 51,
        "SUMMONS_DATE": "06/2019",
        "BORO": "NEW YORK",
        "JURISDICTION_CODE": "0",
        "AGE_GROUP": "18-24",
        "SEX": "M",
        "RACE": "BLACK"
    },
    {
        "count": 7,
        "SUMMONS_DATE": "06/2019",
        "BORO": "BROOKLYN",
        "JURISDICTION_CODE": "1",
        "AGE_GROUP": "25-44",
        "SEX": "M",
        "RACE": "BLACK"
    },
    {
        "count": 17,
        "SUMMONS_DATE": "06/2019",
        "BORO": "STATEN ISLAND",
        "JURISDICTION_CODE": "0",
        "AGE_GROUP": "25-44",
        "SEX": "M",
        "RACE": "WHITE"
    },
    {
        "count": 25,
        "SUMMONS_DATE": "06/2019",
        "BORO": "BRONX",
        "JURISDICTION_CODE": "0",
        "AGE_GROUP": "25-44",
        "SEX": "F",
        "RACE": "WHITE HISPANIC"
    },
    {
        "count": 1,
        "SUMMONS_DATE": "06/2019",
        "BORO": "QUEENS",
        "JURISDICTION_CODE": "0",
        "AGE_GROUP": "<18",
        "SEX": "F",
        "RACE": "WHITE HISPANIC"
    },
    {
        "count": 2,
        "SUMMONS_DATE": "06/2019",
        "BORO": "BRONX",
        "JURISDICTION_CODE": "0",
        "AGE_GROUP": "65+",
        "SEX": "M",
        "RACE": "BLACK"
    },
    {
        "count": 19,
        "SUMMONS_DATE": "06/2019",
        "BORO": "BRONX",
        "JURISDICTION_CODE": "0",
        "AGE_GROUP": "45-64",
        "SEX": "M",
        "RACE": "BLACK HISPANIC"
    },
    {
        "count": 17,
        "SUMMONS_DATE": "06/2019",
        "BORO": "QUEENS",
        "JURISDICTION_CODE": "0",
        "AGE_GROUP": "45-64",
        "SEX": "M",
        "RACE": "ASIAN / PACIFIC ISLANDER"
    },
    {
        "count": 8,
        "SUMMONS_DATE": "06/2019",
        "BORO": "BRONX",
        "JURISDICTION_CODE": "0",
        "AGE_GROUP": "18-24",
        "SEX": "F",
        "RACE": "BLACK HISPANIC"
    },
    {
        "count": 7,
        "SUMMONS_DATE": "06/2019",
        "BORO": "STATEN ISLAND",
        "JURISDICTION_CODE": "0",
        "AGE_GROUP": "45-64",
        "SEX": "M",
        "RACE": "WHITE HISPANIC"
    },
    {
        "count": 37,
        "SUMMONS_DATE": "06/2019",
        "BORO": "BRONX",
        "JURISDICTION_CODE": "2",
        "AGE_GROUP": "25-44",
        "SEX": "M",
        "RACE": "BLACK"
    },
    {
        "count": 22,
        "SUMMONS_DATE": "06/2019",
        "BORO": "NEW YORK",
        "JURISDICTION_CODE": "0",
        "AGE_GROUP": "18-24",
        "SEX": "M",
        "RACE": "BLACK HISPANIC"
    },
    {
        "count": 41,
        "SUMMONS_DATE": "06/2019",
        "BORO": "BROOKLYN",
        "JURISDICTION_CODE": "0",
        "AGE_GROUP": "18-24",
        "SEX": "M",
        "RACE": "WHITE HISPANIC"
    },
    {
        "count": 42,
        "SUMMONS_DATE": "06/2019",
        "BORO": "BRONX",
        "JURISDICTION_CODE": "0",
        "AGE_GROUP": "45-64",
        "SEX": "M",
        "RACE": "WHITE HISPANIC"
    },
    {
        "count": 133,
        "SUMMONS_DATE": "06/2019",
        "BORO": "BRONX",
        "JURISDICTION_CODE": "0",
        "AGE_GROUP": "18-24",
        "SEX": "M",
        "RACE": "BLACK"
    },
    {
        "count": 10,
        "SUMMONS_DATE": "06/2019",
        "BORO": "QUEENS",
        "JURISDICTION_CODE": "0",
        "AGE_GROUP": "25-44",
        "SEX": "F",
        "RACE": "BLACK"
    },
    {
        "count": 51,
        "SUMMONS_DATE": "06/2019",
        "BORO": "BROOKLYN",
        "JURISDICTION_CODE": "0",
        "AGE_GROUP": "25-44",
        "SEX": "M",
        "RACE": "UNKNOWN"
    },
    {
        "count": 10,
        "SUMMONS_DATE": "06/2019",
        "BORO": "BROOKLYN",
        "JURISDICTION_CODE": "0",
        "AGE_GROUP": "18-24",
        "SEX": "F",
        "RACE": "WHITE HISPANIC"
    },
    {
        "count": 30,
        "SUMMONS_DATE": "06/2019",
        "BORO": "QUEENS",
        "JURISDICTION_CODE": "0",
        "AGE_GROUP": "45-64",
        "SEX": "M",
        "RACE": "WHITE HISPANIC"
    },
    {
        "count": 26,
        "SUMMONS_DATE": "06/2019",
        "BORO": "BROOKLYN",
        "JURISDICTION_CODE": "0",
        "AGE_GROUP": "45-64",
        "SEX": "M",
        "RACE": "WHITE"
    },
    {
        "count": 26,
        "SUMMONS_DATE": "06/2019",
        "BORO": "BROOKLYN",
        "JURISDICTION_CODE": "0",
        "AGE_GROUP": "18-24",
        "SEX": "F",
        "RACE": "BLACK"
    },
    {
        "count": 11,
        "SUMMONS_DATE": "06/2019",
        "BORO": "BRONX",
        "JURISDICTION_CODE": "0",
        "AGE_GROUP": "25-44",
        "SEX": "M",
        "RACE": "WHITE"
    },
    {
        "count": 14,
        "SUMMONS_DATE": "06/2019",
        "BORO": "BRONX",
        "JURISDICTION_CODE": "0",
        "AGE_GROUP": "<18",
        "SEX": "M",
        "RACE": "WHITE HISPANIC"
    },
    {
        "count": 6,
        "SUMMONS_DATE": "06/2019",
        "BORO": "BRONX",
        "JURISDICTION_CODE": "2",
        "AGE_GROUP": "25-44",
        "SEX": "F",
        "RACE": "BLACK"
    },
    {
        "count": 4,
        "SUMMONS_DATE": "06/2019",
        "BORO": "BRONX",
        "JURISDICTION_CODE": "0",
        "AGE_GROUP": "45-64",
        "SEX": "F",
        "RACE": "BLACK"
    },
    {
        "count": 14,
        "SUMMONS_DATE": "06/2019",
        "BORO": "QUEENS",
        "JURISDICTION_CODE": "0",
        "AGE_GROUP": "18-24",
        "SEX": "F",
        "RACE": "BLACK"
    },
    {
        "count": 4,
        "SUMMONS_DATE": "06/2019",
        "BORO": "BROOKLYN",
        "JURISDICTION_CODE": "0",
        "AGE_GROUP": "UNKNOWN",
        "SEX": "M",
        "RACE": "BLACK"
    },
    {
        "count": 17,
        "SUMMONS_DATE": "06/2019",
        "BORO": "BROOKLYN",
        "JURISDICTION_CODE": "0",
        "AGE_GROUP": "45-64",
        "SEX": "M",
        "RACE": "ASIAN / PACIFIC ISLANDER"
    },
    {
        "count": 7,
        "SUMMONS_DATE": "06/2019",
        "BORO": "STATEN ISLAND",
        "JURISDICTION_CODE": "0",
        "AGE_GROUP": "25-44",
        "SEX": "F",
        "RACE": "BLACK"
    },
    {
        "count": 7,
        "SUMMONS_DATE": "06/2019",
        "BORO": "BRONX",
        "JURISDICTION_CODE": "2",
        "AGE_GROUP": "<18",
        "SEX": "M",
        "RACE": "BLACK"
    },
    {
        "count": 8,
        "SUMMONS_DATE": "06/2019",
        "BORO": "BROOKLYN",
        "JURISDICTION_CODE": "2",
        "AGE_GROUP": "45-64",
        "SEX": "M",
        "RACE": "BLACK"
    },
    {
        "count": 100,
        "SUMMONS_DATE": "06/2019",
        "BORO": "STATEN ISLAND",
        "JURISDICTION_CODE": "0",
        "AGE_GROUP": "UNKNOWN",
        "SEX": "",
        "RACE": ""
    },
    {
        "count": 17,
        "SUMMONS_DATE": "06/2019",
        "BORO": "BRONX",
        "JURISDICTION_CODE": "0",
        "AGE_GROUP": "<18",
        "SEX": "M",
        "RACE": "BLACK HISPANIC"
    },
    {
        "count": 1,
        "SUMMONS_DATE": "06/2019",
        "BORO": "QUEENS",
        "JURISDICTION_CODE": "1",
        "AGE_GROUP": "45-64",
        "SEX": "M",
        "RACE": "WHITE HISPANIC"
    },
    {
        "count": 19,
        "SUMMONS_DATE": "06/2019",
        "BORO": "BRONX",
        "JURISDICTION_CODE": "1",
        "AGE_GROUP": "25-44",
        "SEX": "M",
        "RACE": "WHITE HISPANIC"
    },
    {
        "count": 11,
        "SUMMONS_DATE": "06/2019",
        "BORO": "NEW YORK",
        "JURISDICTION_CODE": "0",
        "AGE_GROUP": "25-44",
        "SEX": "F",
        "RACE": "WHITE HISPANIC"
    },
    {
        "count": 11,
        "SUMMONS_DATE": "06/2019",
        "BORO": "BRONX",
        "JURISDICTION_CODE": "0",
        "AGE_GROUP": "45-64",
        "SEX": "M",
        "RACE": "WHITE"
    },
    {
        "count": 817,
        "SUMMONS_DATE": "06/2019",
        "BORO": "NEW YORK",
        "JURISDICTION_CODE": "0",
        "AGE_GROUP": "UNKNOWN",
        "SEX": "",
        "RACE": ""
    },
    {
        "count": 760,
        "SUMMONS_DATE": "06/2019",
        "BORO": "BROOKLYN",
        "JURISDICTION_CODE": "0",
        "AGE_GROUP": "UNKNOWN",
        "SEX": "",
        "RACE": ""
    },
    {
        "count": 11,
        "SUMMONS_DATE": "06/2019",
        "BORO": "NEW YORK",
        "JURISDICTION_CODE": "0",
        "AGE_GROUP": "45-64",
        "SEX": "M",
        "RACE": "WHITE HISPANIC"
    },
    {
        "count": 3,
        "SUMMONS_DATE": "06/2019",
        "BORO": "BROOKLYN",
        "JURISDICTION_CODE": "0",
        "AGE_GROUP": "45-64",
        "SEX": "M",
        "RACE": "BLACK HISPANIC"
    },
    {
        "count": 1,
        "SUMMONS_DATE": "06/2019",
        "BORO": "BROOKLYN",
        "JURISDICTION_CODE": "2",
        "AGE_GROUP": "UNKNOWN",
        "SEX": "M",
        "RACE": "BLACK HISPANIC"
    },
    {
        "count": 20,
        "SUMMONS_DATE": "06/2019",
        "BORO": "NEW YORK",
        "JURISDICTION_CODE": "0",
        "AGE_GROUP": "18-24",
        "SEX": "M",
        "RACE": "ASIAN / PACIFIC ISLANDER"
    },
    {
        "count": 16,
        "SUMMONS_DATE": "06/2019",
        "BORO": "BRONX",
        "JURISDICTION_CODE": "1",
        "AGE_GROUP": "18-24",
        "SEX": "M",
        "RACE": "BLACK"
    },
    {
        "count": 3,
        "SUMMONS_DATE": "06/2019",
        "BORO": "NEW YORK",
        "JURISDICTION_CODE": "0",
        "AGE_GROUP": "45-64",
        "SEX": "M",
        "RACE": "AMERICAN INDIAN/ALASKAN NATIVE"
    },
    {
        "count": 11,
        "SUMMONS_DATE": "06/2019",
        "BORO": "NEW YORK",
        "JURISDICTION_CODE": "2",
        "AGE_GROUP": "25-44",
        "SEX": "M",
        "RACE": "BLACK"
    },
    {
        "count": 23,
        "SUMMONS_DATE": "06/2019",
        "BORO": "BRONX",
        "JURISDICTION_CODE": "0",
        "AGE_GROUP": "25-44",
        "SEX": "F",
        "RACE": "BLACK"
    },
    {
        "count": 12,
        "SUMMONS_DATE": "06/2019",
        "BORO": "BRONX",
        "JURISDICTION_CODE": "0",
        "AGE_GROUP": "25-44",
        "SEX": "F",
        "RACE": "BLACK HISPANIC"
    },
    {
        "count": 7,
        "SUMMONS_DATE": "06/2019",
        "BORO": "QUEENS",
        "JURISDICTION_CODE": "0",
        "AGE_GROUP": "18-24",
        "SEX": "M",
        "RACE": "BLACK HISPANIC"
    },
    {
        "count": 7,
        "SUMMONS_DATE": "06/2019",
        "BORO": "BROOKLYN",
        "JURISDICTION_CODE": "0",
        "AGE_GROUP": "25-44",
        "SEX": "F",
        "RACE": "WHITE HISPANIC"
    },
    {
        "count": 9,
        "SUMMONS_DATE": "06/2019",
        "BORO": "NEW YORK",
        "JURISDICTION_CODE": "2",
        "AGE_GROUP": "45-64",
        "SEX": "M",
        "RACE": "BLACK"
    },
    {
        "count": 2,
        "SUMMONS_DATE": "06/2019",
        "BORO": "BRONX",
        "JURISDICTION_CODE": "1",
        "AGE_GROUP": "25-44",
        "SEX": "F",
        "RACE": "WHITE HISPANIC"
    },
    {
        "count": 79,
        "SUMMONS_DATE": "06/2019",
        "BORO": "NEW YORK",
        "JURISDICTION_CODE": "0",
        "AGE_GROUP": "25-44",
        "SEX": "M",
        "RACE": "BLACK HISPANIC"
    },
    {
        "count": 2,
        "SUMMONS_DATE": "06/2019",
        "BORO": "NEW YORK",
        "JURISDICTION_CODE": "1",
        "AGE_GROUP": "45-64",
        "SEX": "F",
        "RACE": "WHITE HISPANIC"
    },
    {
        "count": 3,
        "SUMMONS_DATE": "06/2019",
        "BORO": "NEW YORK",
        "JURISDICTION_CODE": "0",
        "AGE_GROUP": "18-24",
        "SEX": "M",
        "RACE": "AMERICAN INDIAN/ALASKAN NATIVE"
    },
    {
        "count": 15,
        "SUMMONS_DATE": "06/2019",
        "BORO": "NEW YORK",
        "JURISDICTION_CODE": "1",
        "AGE_GROUP": "25-44",
        "SEX": "M",
        "RACE": "WHITE HISPANIC"
    },
    {
        "count": 4,
        "SUMMONS_DATE": "06/2019",
        "BORO": "BRONX",
        "JURISDICTION_CODE": "0",
        "AGE_GROUP": "25-44",
        "SEX": "M",
        "RACE": "OTHER"
    },
    {
        "count": 1,
        "SUMMONS_DATE": "06/2019",
        "BORO": "NEW YORK",
        "JURISDICTION_CODE": "0",
        "AGE_GROUP": "UNKNOWN",
        "SEX": "M",
        "RACE": "BLACK HISPANIC"
    },
    {
        "count": 3,
        "SUMMONS_DATE": "06/2019",
        "BORO": "NEW YORK",
        "JURISDICTION_CODE": "1",
        "AGE_GROUP": "18-24",
        "SEX": "M",
        "RACE": "WHITE"
    },
    {
        "count": 3,
        "SUMMONS_DATE": "06/2019",
        "BORO": "BROOKLYN",
        "JURISDICTION_CODE": "1",
        "AGE_GROUP": "25-44",
        "SEX": "M",
        "RACE": "WHITE"
    },
    {
        "count": 11,
        "SUMMONS_DATE": "06/2019",
        "BORO": "NEW YORK",
        "JURISDICTION_CODE": "0",
        "AGE_GROUP": "18-24",
        "SEX": "F",
        "RACE": "BLACK"
    },
    {
        "count": 5,
        "SUMMONS_DATE": "06/2019",
        "BORO": "BRONX",
        "JURISDICTION_CODE": "0",
        "AGE_GROUP": "65+",
        "SEX": "M",
        "RACE": "WHITE HISPANIC"
    },
    {
        "count": 9,
        "SUMMONS_DATE": "06/2019",
        "BORO": "NEW YORK",
        "JURISDICTION_CODE": "1",
        "AGE_GROUP": "45-64",
        "SEX": "M",
        "RACE": "WHITE HISPANIC"
    },
    {
        "count": 14,
        "SUMMONS_DATE": "06/2019",
        "BORO": "QUEENS",
        "JURISDICTION_CODE": "0",
        "AGE_GROUP": "25-44",
        "SEX": "M",
        "RACE": "WHITE"
    },
    {
        "count": 12,
        "SUMMONS_DATE": "06/2019",
        "BORO": "STATEN ISLAND",
        "JURISDICTION_CODE": "0",
        "AGE_GROUP": "18-24",
        "SEX": "M",
        "RACE": "WHITE"
    },
    {
        "count": 1,
        "SUMMONS_DATE": "06/2019",
        "BORO": "QUEENS",
        "JURISDICTION_CODE": "1",
        "AGE_GROUP": "18-24",
        "SEX": "M",
        "RACE": "BLACK"
    },
    {
        "count": 10,
        "SUMMONS_DATE": "06/2019",
        "BORO": "BRONX",
        "JURISDICTION_CODE": "1",
        "AGE_GROUP": "45-64",
        "SEX": "M",
        "RACE": "WHITE HISPANIC"
    },
    {
        "count": 7,
        "SUMMONS_DATE": "06/2019",
        "BORO": "BRONX",
        "JURISDICTION_CODE": "0",
        "AGE_GROUP": "25-44",
        "SEX": "M",
        "RACE": "ASIAN / PACIFIC ISLANDER"
    },
    {
        "count": 17,
        "SUMMONS_DATE": "06/2019",
        "BORO": "QUEENS",
        "JURISDICTION_CODE": "0",
        "AGE_GROUP": "45-64",
        "SEX": "M",
        "RACE": "UNKNOWN"
    },
    {
        "count": 3,
        "SUMMONS_DATE": "06/2019",
        "BORO": "BRONX",
        "JURISDICTION_CODE": "1",
        "AGE_GROUP": "25-44",
        "SEX": "F",
        "RACE": "BLACK"
    },
    {
        "count": 6,
        "SUMMONS_DATE": "06/2019",
        "BORO": "NEW YORK",
        "JURISDICTION_CODE": "0",
        "AGE_GROUP": "<18",
        "SEX": "M",
        "RACE": "BLACK"
    },
    {
        "count": 1,
        "SUMMONS_DATE": "06/2019",
        "BORO": "NEW YORK",
        "JURISDICTION_CODE": "2",
        "AGE_GROUP": "25-44",
        "SEX": "F",
        "RACE": "BLACK"
    },
    {
        "count": 14,
        "SUMMONS_DATE": "06/2019",
        "BORO": "BRONX",
        "JURISDICTION_CODE": "2",
        "AGE_GROUP": "18-24",
        "SEX": "M",
        "RACE": "WHITE HISPANIC"
    },
    {
        "count": 1,
        "SUMMONS_DATE": "06/2019",
        "BORO": "NEW YORK",
        "JURISDICTION_CODE": "0",
        "AGE_GROUP": "65+",
        "SEX": "M",
        "RACE": "WHITE"
    },
    {
        "count": 8,
        "SUMMONS_DATE": "06/2019",
        "BORO": "BROOKLYN",
        "JURISDICTION_CODE": "2",
        "AGE_GROUP": "<18",
        "SEX": "M",
        "RACE": "BLACK"
    },
    {
        "count": 1,
        "SUMMONS_DATE": "06/2019",
        "BORO": "STATEN ISLAND",
        "JURISDICTION_CODE": "0",
        "AGE_GROUP": "<18",
        "SEX": "F",
        "RACE": "BLACK"
    },
    {
        "count": 19,
        "SUMMONS_DATE": "06/2019",
        "BORO": "NEW YORK",
        "JURISDICTION_CODE": "0",
        "AGE_GROUP": "25-44",
        "SEX": "M",
        "RACE": "ASIAN / PACIFIC ISLANDER"
    },
    {
        "count": 24,
        "SUMMONS_DATE": "06/2019",
        "BORO": "BRONX",
        "JURISDICTION_CODE": "1",
        "AGE_GROUP": "45-64",
        "SEX": "M",
        "RACE": "BLACK"
    },
    {
        "count": 1,
        "SUMMONS_DATE": "06/2019",
        "BORO": "STATEN ISLAND",
        "JURISDICTION_CODE": "0",
        "AGE_GROUP": "<18",
        "SEX": "M",
        "RACE": "BLACK"
    },
    {
        "count": 2,
        "SUMMONS_DATE": "06/2019",
        "BORO": "BROOKLYN",
        "JURISDICTION_CODE": "0",
        "AGE_GROUP": "45-64",
        "SEX": "F",
        "RACE": "BLACK HISPANIC"
    },
    {
        "count": 30,
        "SUMMONS_DATE": "06/2019",
        "BORO": "BRONX",
        "JURISDICTION_CODE": "2",
        "AGE_GROUP": "18-24",
        "SEX": "M",
        "RACE": "BLACK"
    },
    {
        "count": 8,
        "SUMMONS_DATE": "06/2019",
        "BORO": "BRONX",
        "JURISDICTION_CODE": "2",
        "AGE_GROUP": "45-64",
        "SEX": "M",
        "RACE": "BLACK"
    },
    {
        "count": 13,
        "SUMMONS_DATE": "06/2019",
        "BORO": "BRONX",
        "JURISDICTION_CODE": "2",
        "AGE_GROUP": "18-24",
        "SEX": "M",
        "RACE": "BLACK HISPANIC"
    },
    {
        "count": 2,
        "SUMMONS_DATE": "06/2019",
        "BORO": "NEW YORK",
        "JURISDICTION_CODE": "2",
        "AGE_GROUP": "25-44",
        "SEX": "F",
        "RACE": "WHITE HISPANIC"
    },
    {
        "count": 17,
        "SUMMONS_DATE": "06/2019",
        "BORO": "BRONX",
        "JURISDICTION_CODE": "0",
        "AGE_GROUP": "18-24",
        "SEX": "F",
        "RACE": "BLACK"
    },
    {
        "count": 8,
        "SUMMONS_DATE": "06/2019",
        "BORO": "STATEN ISLAND",
        "JURISDICTION_CODE": "0",
        "AGE_GROUP": "18-24",
        "SEX": "F",
        "RACE": "BLACK"
    },
    {
        "count": 1,
        "SUMMONS_DATE": "06/2019",
        "BORO": "NEW YORK",
        "JURISDICTION_CODE": "0",
        "AGE_GROUP": "UNKNOWN",
        "SEX": "M",
        "RACE": "WHITE HISPANIC"
    },
    {
        "count": 1,
        "SUMMONS_DATE": "06/2019",
        "BORO": "BRONX",
        "JURISDICTION_CODE": "2",
        "AGE_GROUP": "UNKNOWN",
        "SEX": "F",
        "RACE": "WHITE HISPANIC"
    },
    {
        "count": 2,
        "SUMMONS_DATE": "06/2019",
        "BORO": "QUEENS",
        "JURISDICTION_CODE": "0",
        "AGE_GROUP": "18-24",
        "SEX": "F",
        "RACE": "AMERICAN INDIAN/ALASKAN NATIVE"
    },
    {
        "count": 2,
        "SUMMONS_DATE": "06/2019",
        "BORO": "NEW YORK",
        "JURISDICTION_CODE": "1",
        "AGE_GROUP": "<18",
        "SEX": "M",
        "RACE": "BLACK"
    },
    {
        "count": 8,
        "SUMMONS_DATE": "06/2019",
        "BORO": "BROOKLYN",
        "JURISDICTION_CODE": "0",
        "AGE_GROUP": "18-24",
        "SEX": "M",
        "RACE": "ASIAN / PACIFIC ISLANDER"
    },
    {
        "count": 1,
        "SUMMONS_DATE": "06/2019",
        "BORO": "BROOKLYN",
        "JURISDICTION_CODE": "2",
        "AGE_GROUP": "<18",
        "SEX": "M",
        "RACE": "WHITE HISPANIC"
    },
    {
        "count": 9,
        "SUMMONS_DATE": "06/2019",
        "BORO": "QUEENS",
        "JURISDICTION_CODE": "0",
        "AGE_GROUP": "18-24",
        "SEX": "M",
        "RACE": "WHITE"
    },
    {
        "count": 8,
        "SUMMONS_DATE": "06/2019",
        "BORO": "NEW YORK",
        "JURISDICTION_CODE": "2",
        "AGE_GROUP": "18-24",
        "SEX": "M",
        "RACE": "BLACK"
    },
    {
        "count": 1,
        "SUMMONS_DATE": "06/2019",
        "BORO": "NEW YORK",
        "JURISDICTION_CODE": "0",
        "AGE_GROUP": "25-44",
        "SEX": "U",
        "RACE": "ASIAN / PACIFIC ISLANDER"
    },
    {
        "count": 8,
        "SUMMONS_DATE": "06/2019",
        "BORO": "BROOKLYN",
        "JURISDICTION_CODE": "0",
        "AGE_GROUP": "25-44",
        "SEX": "F",
        "RACE": "WHITE"
    },
    {
        "count": 3,
        "SUMMONS_DATE": "06/2019",
        "BORO": "QUEENS",
        "JURISDICTION_CODE": "2",
        "AGE_GROUP": "18-24",
        "SEX": "M",
        "RACE": "BLACK"
    },
    {
        "count": 1,
        "SUMMONS_DATE": "06/2019",
        "BORO": "BROOKLYN",
        "JURISDICTION_CODE": "0",
        "AGE_GROUP": "25-44",
        "SEX": "U",
        "RACE": "WHITE HISPANIC"
    },
    {
        "count": 1,
        "SUMMONS_DATE": "06/2019",
        "BORO": "BRONX",
        "JURISDICTION_CODE": "0",
        "AGE_GROUP": "UNKNOWN",
        "SEX": "M",
        "RACE": "WHITE HISPANIC"
    },
    {
        "count": 3,
        "SUMMONS_DATE": "06/2019",
        "BORO": "STATEN ISLAND",
        "JURISDICTION_CODE": "0",
        "AGE_GROUP": "25-44",
        "SEX": "F",
        "RACE": "WHITE"
    },
    {
        "count": 3,
        "SUMMONS_DATE": "06/2019",
        "BORO": "BROOKLYN",
        "JURISDICTION_CODE": "0",
        "AGE_GROUP": "45-64",
        "SEX": "F",
        "RACE": "WHITE HISPANIC"
    },
    {
        "count": 5,
        "SUMMONS_DATE": "06/2019",
        "BORO": "NEW YORK",
        "JURISDICTION_CODE": "1",
        "AGE_GROUP": "18-24",
        "SEX": "M",
        "RACE": "WHITE HISPANIC"
    },
    {
        "count": 1,
        "SUMMONS_DATE": "06/2019",
        "BORO": "QUEENS",
        "JURISDICTION_CODE": "0",
        "AGE_GROUP": "45-64",
        "SEX": "M",
        "RACE": "BLACK HISPANIC"
    },
    {
        "count": 9,
        "SUMMONS_DATE": "06/2019",
        "BORO": "QUEENS",
        "JURISDICTION_CODE": "0",
        "AGE_GROUP": "45-64",
        "SEX": "M",
        "RACE": "WHITE"
    },
    {
        "count": 1,
        "SUMMONS_DATE": "06/2019",
        "BORO": "QUEENS",
        "JURISDICTION_CODE": "0",
        "AGE_GROUP": "18-24",
        "SEX": "M",
        "RACE": "AMERICAN INDIAN/ALASKAN NATIVE"
    },
    {
        "count": 4,
        "SUMMONS_DATE": "06/2019",
        "BORO": "BROOKLYN",
        "JURISDICTION_CODE": "0",
        "AGE_GROUP": "65+",
        "SEX": "M",
        "RACE": "ASIAN / PACIFIC ISLANDER"
    },
    {
        "count": 21,
        "SUMMONS_DATE": "06/2019",
        "BORO": "BROOKLYN",
        "JURISDICTION_CODE": "0",
        "AGE_GROUP": "45-64",
        "SEX": "M",
        "RACE": "UNKNOWN"
    },
    {
        "count": 4,
        "SUMMONS_DATE": "06/2019",
        "BORO": "QUEENS",
        "JURISDICTION_CODE": "0",
        "AGE_GROUP": "25-44",
        "SEX": "F",
        "RACE": "WHITE"
    },
    {
        "count": 5,
        "SUMMONS_DATE": "06/2019",
        "BORO": "BRONX",
        "JURISDICTION_CODE": "1",
        "AGE_GROUP": "45-64",
        "SEX": "M",
        "RACE": "BLACK HISPANIC"
    },
    {
        "count": 14,
        "SUMMONS_DATE": "06/2019",
        "BORO": "NEW YORK",
        "JURISDICTION_CODE": "1",
        "AGE_GROUP": "25-44",
        "SEX": "M",
        "RACE": "WHITE"
    },
    {
        "count": 21,
        "SUMMONS_DATE": "06/2019",
        "BORO": "BRONX",
        "JURISDICTION_CODE": "0",
        "AGE_GROUP": "18-24",
        "SEX": "M",
        "RACE": "WHITE"
    },
    {
        "count": 2,
        "SUMMONS_DATE": "06/2019",
        "BORO": "BRONX",
        "JURISDICTION_CODE": "0",
        "AGE_GROUP": "<18",
        "SEX": "F",
        "RACE": "WHITE HISPANIC"
    },
    {
        "count": 2,
        "SUMMONS_DATE": "06/2019",
        "BORO": "BRONX",
        "JURISDICTION_CODE": "1",
        "AGE_GROUP": "18-24",
        "SEX": "F",
        "RACE": "WHITE HISPANIC"
    },
    {
        "count": 2,
        "SUMMONS_DATE": "06/2019",
        "BORO": "STATEN ISLAND",
        "JURISDICTION_CODE": "0",
        "AGE_GROUP": "65+",
        "SEX": "M",
        "RACE": "BLACK"
    },
    {
        "count": 4,
        "SUMMONS_DATE": "06/2019",
        "BORO": "BRONX",
        "JURISDICTION_CODE": "0",
        "AGE_GROUP": "45-64",
        "SEX": "F",
        "RACE": "WHITE HISPANIC"
    },
    {
        "count": 13,
        "SUMMONS_DATE": "06/2019",
        "BORO": "NEW YORK",
        "JURISDICTION_CODE": "1",
        "AGE_GROUP": "18-24",
        "SEX": "M",
        "RACE": "BLACK"
    },
    {
        "count": 2,
        "SUMMONS_DATE": "06/2019",
        "BORO": "BROOKLYN",
        "JURISDICTION_CODE": "0",
        "AGE_GROUP": "65+",
        "SEX": "M",
        "RACE": "WHITE"
    },
    {
        "count": 1,
        "SUMMONS_DATE": "06/2019",
        "BORO": "QUEENS",
        "JURISDICTION_CODE": "0",
        "AGE_GROUP": "<18",
        "SEX": "M",
        "RACE": "BLACK HISPANIC"
    },
    {
        "count": 2,
        "SUMMONS_DATE": "06/2019",
        "BORO": "NEW YORK",
        "JURISDICTION_CODE": "1",
        "AGE_GROUP": "25-44",
        "SEX": "M",
        "RACE": "ASIAN / PACIFIC ISLANDER"
    },
    {
        "count": 6,
        "SUMMONS_DATE": "06/2019",
        "BORO": "NEW YORK",
        "JURISDICTION_CODE": "0",
        "AGE_GROUP": "18-24",
        "SEX": "F",
        "RACE": "BLACK HISPANIC"
    },
    {
        "count": 1,
        "SUMMONS_DATE": "06/2019",
        "BORO": "QUEENS",
        "JURISDICTION_CODE": "0",
        "AGE_GROUP": "25-44",
        "SEX": "U",
        "RACE": "BLACK"
    },
    {
        "count": 4,
        "SUMMONS_DATE": "06/2019",
        "BORO": "BROOKLYN",
        "JURISDICTION_CODE": "0",
        "AGE_GROUP": "<18",
        "SEX": "M",
        "RACE": "WHITE"
    },
    {
        "count": 1,
        "SUMMONS_DATE": "06/2019",
        "BORO": "BROOKLYN",
        "JURISDICTION_CODE": "0",
        "AGE_GROUP": "25-44",
        "SEX": "M",
        "RACE": "AMERICAN INDIAN/ALASKAN NATIVE"
    },
    {
        "count": 6,
        "SUMMONS_DATE": "06/2019",
        "BORO": "BRONX",
        "JURISDICTION_CODE": "1",
        "AGE_GROUP": "18-24",
        "SEX": "M",
        "RACE": "WHITE HISPANIC"
    },
    {
        "count": 14,
        "SUMMONS_DATE": "06/2019",
        "BORO": "BROOKLYN",
        "JURISDICTION_CODE": "0",
        "AGE_GROUP": "18-24",
        "SEX": "M",
        "RACE": "BLACK HISPANIC"
    },
    {
        "count": 6,
        "SUMMONS_DATE": "06/2019",
        "BORO": "STATEN ISLAND",
        "JURISDICTION_CODE": "0",
        "AGE_GROUP": "25-44",
        "SEX": "M",
        "RACE": "BLACK HISPANIC"
    },
    {
        "count": 3,
        "SUMMONS_DATE": "06/2019",
        "BORO": "BROOKLYN",
        "JURISDICTION_CODE": "1",
        "AGE_GROUP": "18-24",
        "SEX": "M",
        "RACE": "WHITE HISPANIC"
    },
    {
        "count": 2,
        "SUMMONS_DATE": "06/2019",
        "BORO": "BROOKLYN",
        "JURISDICTION_CODE": "2",
        "AGE_GROUP": "45-64",
        "SEX": "M",
        "RACE": "WHITE HISPANIC"
    },
    {
        "count": 18,
        "SUMMONS_DATE": "06/2019",
        "BORO": "NEW YORK",
        "JURISDICTION_CODE": "0",
        "AGE_GROUP": "45-64",
        "SEX": "M",
        "RACE": "ASIAN / PACIFIC ISLANDER"
    },
    {
        "count": 4,
        "SUMMONS_DATE": "06/2019",
        "BORO": "QUEENS",
        "JURISDICTION_CODE": "0",
        "AGE_GROUP": "<18",
        "SEX": "M",
        "RACE": "BLACK"
    },
    {
        "count": 1,
        "SUMMONS_DATE": "06/2019",
        "BORO": "NEW YORK",
        "JURISDICTION_CODE": "0",
        "AGE_GROUP": "45-64",
        "SEX": "F",
        "RACE": "BLACK HISPANIC"
    },
    {
        "count": 1,
        "SUMMONS_DATE": "06/2019",
        "BORO": "STATEN ISLAND",
        "JURISDICTION_CODE": "0",
        "AGE_GROUP": "45-64",
        "SEX": "F",
        "RACE": "WHITE HISPANIC"
    },
    {
        "count": 4,
        "SUMMONS_DATE": "06/2019",
        "BORO": "NEW YORK",
        "JURISDICTION_CODE": "0",
        "AGE_GROUP": "25-44",
        "SEX": "F",
        "RACE": "BLACK HISPANIC"
    },
    {
        "count": 1,
        "SUMMONS_DATE": "06/2019",
        "BORO": "BRONX",
        "JURISDICTION_CODE": "1",
        "AGE_GROUP": "45-64",
        "SEX": "F",
        "RACE": "BLACK"
    },
    {
        "count": 4,
        "SUMMONS_DATE": "06/2019",
        "BORO": "BROOKLYN",
        "JURISDICTION_CODE": "0",
        "AGE_GROUP": "45-64",
        "SEX": "F",
        "RACE": "BLACK"
    },
    {
        "count": 3,
        "SUMMONS_DATE": "06/2019",
        "BORO": "BROOKLYN",
        "JURISDICTION_CODE": "0",
        "AGE_GROUP": "<18",
        "SEX": "F",
        "RACE": "BLACK"
    },
    {
        "count": 3,
        "SUMMONS_DATE": "06/2019",
        "BORO": "BROOKLYN",
        "JURISDICTION_CODE": "0",
        "AGE_GROUP": "25-44",
        "SEX": "F",
        "RACE": "BLACK HISPANIC"
    },
    {
        "count": 5,
        "SUMMONS_DATE": "06/2019",
        "BORO": "BROOKLYN",
        "JURISDICTION_CODE": "0",
        "AGE_GROUP": "65+",
        "SEX": "M",
        "RACE": "BLACK"
    },
    {
        "count": 6,
        "SUMMONS_DATE": "06/2019",
        "BORO": "NEW YORK",
        "JURISDICTION_CODE": "0",
        "AGE_GROUP": "45-64",
        "SEX": "M",
        "RACE": "WHITE"
    },
    {
        "count": 16,
        "SUMMONS_DATE": "06/2019",
        "BORO": "NEW YORK",
        "JURISDICTION_CODE": "0",
        "AGE_GROUP": "25-44",
        "SEX": "M",
        "RACE": "UNKNOWN"
    },
    {
        "count": 1,
        "SUMMONS_DATE": "06/2019",
        "BORO": "STATEN ISLAND",
        "JURISDICTION_CODE": "0",
        "AGE_GROUP": "45-64",
        "SEX": "M",
        "RACE": "AMERICAN INDIAN/ALASKAN NATIVE"
    },
    {
        "count": 7,
        "SUMMONS_DATE": "06/2019",
        "BORO": "BRONX",
        "JURISDICTION_CODE": "2",
        "AGE_GROUP": "45-64",
        "SEX": "M",
        "RACE": "WHITE HISPANIC"
    },
    {
        "count": 5,
        "SUMMONS_DATE": "06/2019",
        "BORO": "STATEN ISLAND",
        "JURISDICTION_CODE": "0",
        "AGE_GROUP": "18-24",
        "SEX": "M",
        "RACE": "WHITE HISPANIC"
    },
    {
        "count": 1,
        "SUMMONS_DATE": "06/2019",
        "BORO": "STATEN ISLAND",
        "JURISDICTION_CODE": "0",
        "AGE_GROUP": "18-24",
        "SEX": "F",
        "RACE": "WHITE HISPANIC"
    },
    {
        "count": 3,
        "SUMMONS_DATE": "06/2019",
        "BORO": "NEW YORK",
        "JURISDICTION_CODE": "0",
        "AGE_GROUP": "25-44",
        "SEX": "M",
        "RACE": "OTHER"
    },
    {
        "count": 3,
        "SUMMONS_DATE": "06/2019",
        "BORO": "STATEN ISLAND",
        "JURISDICTION_CODE": "0",
        "AGE_GROUP": "18-24",
        "SEX": "F",
        "RACE": "WHITE"
    },
    {
        "count": 1,
        "SUMMONS_DATE": "06/2019",
        "BORO": "NEW YORK",
        "JURISDICTION_CODE": "0",
        "AGE_GROUP": "<18",
        "SEX": "M",
        "RACE": "BLACK HISPANIC"
    },
    {
        "count": 6,
        "SUMMONS_DATE": "06/2019",
        "BORO": "NEW YORK",
        "JURISDICTION_CODE": "0",
        "AGE_GROUP": "18-24",
        "SEX": "M",
        "RACE": "UNKNOWN"
    },
    {
        "count": 5,
        "SUMMONS_DATE": "06/2019",
        "BORO": "NEW YORK",
        "JURISDICTION_CODE": "0",
        "AGE_GROUP": "18-24",
        "SEX": "F",
        "RACE": "WHITE HISPANIC"
    },
    {
        "count": 1,
        "SUMMONS_DATE": "06/2019",
        "BORO": "BROOKLYN",
        "JURISDICTION_CODE": "0",
        "AGE_GROUP": "65+",
        "SEX": "M",
        "RACE": "AMERICAN INDIAN/ALASKAN NATIVE"
    },
    {
        "count": 4,
        "SUMMONS_DATE": "06/2019",
        "BORO": "QUEENS",
        "JURISDICTION_CODE": "0",
        "AGE_GROUP": "18-24",
        "SEX": "F",
        "RACE": "WHITE HISPANIC"
    },
    {
        "count": 7,
        "SUMMONS_DATE": "06/2019",
        "BORO": "BRONX",
        "JURISDICTION_CODE": "1",
        "AGE_GROUP": "25-44",
        "SEX": "M",
        "RACE": "BLACK HISPANIC"
    },
    {
        "count": 5,
        "SUMMONS_DATE": "06/2019",
        "BORO": "BROOKLYN",
        "JURISDICTION_CODE": "2",
        "AGE_GROUP": "25-44",
        "SEX": "F",
        "RACE": "BLACK"
    },
    {
        "count": 10,
        "SUMMONS_DATE": "06/2019",
        "BORO": "NEW YORK",
        "JURISDICTION_CODE": "2",
        "AGE_GROUP": "25-44",
        "SEX": "M",
        "RACE": "WHITE HISPANIC"
    },
    {
        "count": 5,
        "SUMMONS_DATE": "06/2019",
        "BORO": "BRONX",
        "JURISDICTION_CODE": "0",
        "AGE_GROUP": "UNKNOWN",
        "SEX": "M",
        "RACE": "BLACK"
    },
    {
        "count": 6,
        "SUMMONS_DATE": "06/2019",
        "BORO": "BRONX",
        "JURISDICTION_CODE": "1",
        "AGE_GROUP": "18-24",
        "SEX": "M",
        "RACE": "BLACK HISPANIC"
    },
    {
        "count": 1,
        "SUMMONS_DATE": "06/2019",
        "BORO": "NEW YORK",
        "JURISDICTION_CODE": "0",
        "AGE_GROUP": "45-64",
        "SEX": "F",
        "RACE": "WHITE HISPANIC"
    },
    {
        "count": 1,
        "SUMMONS_DATE": "06/2019",
        "BORO": "BRONX",
        "JURISDICTION_CODE": "0",
        "AGE_GROUP": "45-64",
        "SEX": "M",
        "RACE": "OTHER"
    },
    {
        "count": 4,
        "SUMMONS_DATE": "06/2019",
        "BORO": "NEW YORK",
        "JURISDICTION_CODE": "1",
        "AGE_GROUP": "25-44",
        "SEX": "F",
        "RACE": "BLACK"
    },
    {
        "count": 3,
        "SUMMONS_DATE": "06/2019",
        "BORO": "NEW YORK",
        "JURISDICTION_CODE": "2",
        "AGE_GROUP": "<18",
        "SEX": "M",
        "RACE": "BLACK"
    },
    {
        "count": 1,
        "SUMMONS_DATE": "06/2019",
        "BORO": "NEW YORK",
        "JURISDICTION_CODE": "2",
        "AGE_GROUP": "45-64",
        "SEX": "M",
        "RACE": "BLACK HISPANIC"
    },
    {
        "count": 1,
        "SUMMONS_DATE": "06/2019",
        "BORO": "BROOKLYN",
        "JURISDICTION_CODE": "0",
        "AGE_GROUP": "65+",
        "SEX": "M",
        "RACE": "WHITE HISPANIC"
    },
    {
        "count": 4,
        "SUMMONS_DATE": "06/2019",
        "BORO": "BROOKLYN",
        "JURISDICTION_CODE": "0",
        "AGE_GROUP": "45-64",
        "SEX": "F",
        "RACE": "WHITE"
    },
    {
        "count": 3,
        "SUMMONS_DATE": "06/2019",
        "BORO": "QUEENS",
        "JURISDICTION_CODE": "0",
        "AGE_GROUP": "45-64",
        "SEX": "F",
        "RACE": "ASIAN / PACIFIC ISLANDER"
    },
    {
        "count": 5,
        "SUMMONS_DATE": "06/2019",
        "BORO": "BROOKLYN",
        "JURISDICTION_CODE": "1",
        "AGE_GROUP": "18-24",
        "SEX": "M",
        "RACE": "BLACK"
    },
    {
        "count": 2,
        "SUMMONS_DATE": "06/2019",
        "BORO": "NEW YORK",
        "JURISDICTION_CODE": "2",
        "AGE_GROUP": "45-64",
        "SEX": "M",
        "RACE": "WHITE HISPANIC"
    },
    {
        "count": 3,
        "SUMMONS_DATE": "06/2019",
        "BORO": "QUEENS",
        "JURISDICTION_CODE": "0",
        "AGE_GROUP": "<18",
        "SEX": "M",
        "RACE": "WHITE HISPANIC"
    },
    {
        "count": 1,
        "SUMMONS_DATE": "06/2019",
        "BORO": "NEW YORK",
        "JURISDICTION_CODE": "0",
        "AGE_GROUP": "65+",
        "SEX": "M",
        "RACE": "UNKNOWN"
    },
    {
        "count": 8,
        "SUMMONS_DATE": "06/2019",
        "BORO": "NEW YORK",
        "JURISDICTION_CODE": "1",
        "AGE_GROUP": "45-64",
        "SEX": "M",
        "RACE": "BLACK HISPANIC"
    },
    {
        "count": 3,
        "SUMMONS_DATE": "06/2019",
        "BORO": "NEW YORK",
        "JURISDICTION_CODE": "0",
        "AGE_GROUP": "18-24",
        "SEX": "M",
        "RACE": "OTHER"
    },
    {
        "count": 1,
        "SUMMONS_DATE": "06/2019",
        "BORO": "BRONX",
        "JURISDICTION_CODE": "0",
        "AGE_GROUP": "18-24",
        "SEX": "M",
        "RACE": "ASIAN / PACIFIC ISLANDER"
    },
    {
        "count": 6,
        "SUMMONS_DATE": "06/2019",
        "BORO": "QUEENS",
        "JURISDICTION_CODE": "0",
        "AGE_GROUP": "25-44",
        "SEX": "M",
        "RACE": "BLACK HISPANIC"
    },
    {
        "count": 1,
        "SUMMONS_DATE": "06/2019",
        "BORO": "BROOKLYN",
        "JURISDICTION_CODE": "1",
        "AGE_GROUP": "18-24",
        "SEX": "U",
        "RACE": "WHITE"
    },
    {
        "count": 1,
        "SUMMONS_DATE": "06/2019",
        "BORO": "BRONX",
        "JURISDICTION_CODE": "0",
        "AGE_GROUP": "25-44",
        "SEX": "F",
        "RACE": "WHITE"
    },
    {
        "count": 1,
        "SUMMONS_DATE": "06/2019",
        "BORO": "BROOKLYN",
        "JURISDICTION_CODE": "2",
        "AGE_GROUP": "18-24",
        "SEX": "U",
        "RACE": "WHITE HISPANIC"
    },
    {
        "count": 22,
        "SUMMONS_DATE": "06/2019",
        "BORO": "QUEENS",
        "JURISDICTION_CODE": "0",
        "AGE_GROUP": "25-44",
        "SEX": "M",
        "RACE": "UNKNOWN"
    },
    {
        "count": 1,
        "SUMMONS_DATE": "06/2019",
        "BORO": "QUEENS",
        "JURISDICTION_CODE": "0",
        "AGE_GROUP": "UNKNOWN",
        "SEX": "M",
        "RACE": "BLACK"
    },
    {
        "count": 1,
        "SUMMONS_DATE": "06/2019",
        "BORO": "BRONX",
        "JURISDICTION_CODE": "0",
        "AGE_GROUP": "<18",
        "SEX": "F",
        "RACE": "WHITE"
    },
    {
        "count": 1,
        "SUMMONS_DATE": "06/2019",
        "BORO": "BRONX",
        "JURISDICTION_CODE": "2",
        "AGE_GROUP": "UNKNOWN",
        "SEX": "M",
        "RACE": "BLACK"
    },
    {
        "count": 7,
        "SUMMONS_DATE": "06/2019",
        "BORO": "QUEENS",
        "JURISDICTION_CODE": "0",
        "AGE_GROUP": "65+",
        "SEX": "M",
        "RACE": "BLACK"
    },
    {
        "count": 3,
        "SUMMONS_DATE": "06/2019",
        "BORO": "BROOKLYN",
        "JURISDICTION_CODE": "1",
        "AGE_GROUP": "45-64",
        "SEX": "M",
        "RACE": "BLACK"
    },
    {
        "count": 4,
        "SUMMONS_DATE": "06/2019",
        "BORO": "BRONX",
        "JURISDICTION_CODE": "2",
        "AGE_GROUP": "18-24",
        "SEX": "F",
        "RACE": "WHITE HISPANIC"
    },
    {
        "count": 3,
        "SUMMONS_DATE": "06/2019",
        "BORO": "BRONX",
        "JURISDICTION_CODE": "2",
        "AGE_GROUP": "25-44",
        "SEX": "M",
        "RACE": "UNKNOWN"
    },
    {
        "count": 1,
        "SUMMONS_DATE": "06/2019",
        "BORO": "BRONX",
        "JURISDICTION_CODE": "2",
        "AGE_GROUP": "45-64",
        "SEX": "M",
        "RACE": "BLACK HISPANIC"
    },
    {
        "count": 6,
        "SUMMONS_DATE": "06/2019",
        "BORO": "NEW YORK",
        "JURISDICTION_CODE": "0",
        "AGE_GROUP": "<18",
        "SEX": "M",
        "RACE": "WHITE HISPANIC"
    },
    {
        "count": 6,
        "SUMMONS_DATE": "06/2019",
        "BORO": "BRONX",
        "JURISDICTION_CODE": "2",
        "AGE_GROUP": "<18",
        "SEX": "M",
        "RACE": "WHITE HISPANIC"
    },
    {
        "count": 2,
        "SUMMONS_DATE": "06/2019",
        "BORO": "QUEENS",
        "JURISDICTION_CODE": "0",
        "AGE_GROUP": "18-24",
        "SEX": "F",
        "RACE": "ASIAN / PACIFIC ISLANDER"
    },
    {
        "count": 4,
        "SUMMONS_DATE": "06/2019",
        "BORO": "NEW YORK",
        "JURISDICTION_CODE": "0",
        "AGE_GROUP": "25-44",
        "SEX": "F",
        "RACE": "WHITE"
    },
    {
        "count": 2,
        "SUMMONS_DATE": "06/2019",
        "BORO": "QUEENS",
        "JURISDICTION_CODE": "0",
        "AGE_GROUP": "45-64",
        "SEX": "F",
        "RACE": "AMERICAN INDIAN/ALASKAN NATIVE"
    },
    {
        "count": 4,
        "SUMMONS_DATE": "06/2019",
        "BORO": "QUEENS",
        "JURISDICTION_CODE": "1",
        "AGE_GROUP": "25-44",
        "SEX": "M",
        "RACE": "BLACK"
    },
    {
        "count": 3,
        "SUMMONS_DATE": "06/2019",
        "BORO": "NEW YORK",
        "JURISDICTION_CODE": "2",
        "AGE_GROUP": "18-24",
        "SEX": "M",
        "RACE": "WHITE"
    },
    {
        "count": 2,
        "SUMMONS_DATE": "06/2019",
        "BORO": "NEW YORK",
        "JURISDICTION_CODE": "0",
        "AGE_GROUP": "65+",
        "SEX": "M",
        "RACE": "WHITE HISPANIC"
    },
    {
        "count": 1,
        "SUMMONS_DATE": "06/2019",
        "BORO": "BROOKLYN",
        "JURISDICTION_CODE": "1",
        "AGE_GROUP": "45-64",
        "SEX": "M",
        "RACE": "WHITE HISPANIC"
    },
    {
        "count": 1,
        "SUMMONS_DATE": "06/2019",
        "BORO": "NEW YORK",
        "JURISDICTION_CODE": "1",
        "AGE_GROUP": "45-64",
        "SEX": "U",
        "RACE": "WHITE"
    },
    {
        "count": 2,
        "SUMMONS_DATE": "06/2019",
        "BORO": "NEW YORK",
        "JURISDICTION_CODE": "0",
        "AGE_GROUP": "45-64",
        "SEX": "M",
        "RACE": "UNKNOWN"
    },
    {
        "count": 3,
        "SUMMONS_DATE": "06/2019",
        "BORO": "BRONX",
        "JURISDICTION_CODE": "1",
        "AGE_GROUP": "18-24",
        "SEX": "F",
        "RACE": "BLACK"
    },
    {
        "count": 1,
        "SUMMONS_DATE": "06/2019",
        "BORO": "NEW YORK",
        "JURISDICTION_CODE": "1",
        "AGE_GROUP": "25-44",
        "SEX": "F",
        "RACE": "WHITE"
    },
    {
        "count": 2,
        "SUMMONS_DATE": "06/2019",
        "BORO": "BRONX",
        "JURISDICTION_CODE": "1",
        "AGE_GROUP": "45-64",
        "SEX": "M",
        "RACE": "WHITE"
    },
    {
        "count": 3,
        "SUMMONS_DATE": "06/2019",
        "BORO": "NEW YORK",
        "JURISDICTION_CODE": "0",
        "AGE_GROUP": "25-44",
        "SEX": "F",
        "RACE": "ASIAN / PACIFIC ISLANDER"
    },
    {
        "count": 1,
        "SUMMONS_DATE": "06/2019",
        "BORO": "STATEN ISLAND",
        "JURISDICTION_CODE": "0",
        "AGE_GROUP": "25-44",
        "SEX": "M",
        "RACE": "ASIAN / PACIFIC ISLANDER"
    },
    {
        "count": 1,
        "SUMMONS_DATE": "06/2019",
        "BORO": "BROOKLYN",
        "JURISDICTION_CODE": "2",
        "AGE_GROUP": "25-44",
        "SEX": "U",
        "RACE": "UNKNOWN"
    },
    {
        "count": 5,
        "SUMMONS_DATE": "06/2019",
        "BORO": "BROOKLYN",
        "JURISDICTION_CODE": "0",
        "AGE_GROUP": "18-24",
        "SEX": "M",
        "RACE": "UNKNOWN"
    },
    {
        "count": 4,
        "SUMMONS_DATE": "06/2019",
        "BORO": "BROOKLYN",
        "JURISDICTION_CODE": "0",
        "AGE_GROUP": "18-24",
        "SEX": "F",
        "RACE": "BLACK HISPANIC"
    },
    {
        "count": 2,
        "SUMMONS_DATE": "06/2019",
        "BORO": "BROOKLYN",
        "JURISDICTION_CODE": "0",
        "AGE_GROUP": "18-24",
        "SEX": "M",
        "RACE": "AMERICAN INDIAN/ALASKAN NATIVE"
    },
    {
        "count": 1,
        "SUMMONS_DATE": "06/2019",
        "BORO": "QUEENS",
        "JURISDICTION_CODE": "0",
        "AGE_GROUP": "<18",
        "SEX": "M",
        "RACE": "UNKNOWN"
    },
    {
        "count": 3,
        "SUMMONS_DATE": "06/2019",
        "BORO": "STATEN ISLAND",
        "JURISDICTION_CODE": "0",
        "AGE_GROUP": "25-44",
        "SEX": "F",
        "RACE": "WHITE HISPANIC"
    },
    {
        "count": 2,
        "SUMMONS_DATE": "06/2019",
        "BORO": "NEW YORK",
        "JURISDICTION_CODE": "0",
        "AGE_GROUP": "<18",
        "SEX": "M",
        "RACE": "WHITE"
    },
    {
        "count": 1,
        "SUMMONS_DATE": "06/2019",
        "BORO": "BRONX",
        "JURISDICTION_CODE": "2",
        "AGE_GROUP": "25-44",
        "SEX": "F",
        "RACE": "WHITE HISPANIC"
    },
    {
        "count": 4,
        "SUMMONS_DATE": "06/2019",
        "BORO": "NEW YORK",
        "JURISDICTION_CODE": "2",
        "AGE_GROUP": "25-44",
        "SEX": "M",
        "RACE": "BLACK HISPANIC"
    },
    {
        "count": 1,
        "SUMMONS_DATE": "06/2019",
        "BORO": "BRONX",
        "JURISDICTION_CODE": "0",
        "AGE_GROUP": "18-24",
        "SEX": "M",
        "RACE": "AMERICAN INDIAN/ALASKAN NATIVE"
    },
    {
        "count": 6,
        "SUMMONS_DATE": "06/2019",
        "BORO": "STATEN ISLAND",
        "JURISDICTION_CODE": "0",
        "AGE_GROUP": "45-64",
        "SEX": "M",
        "RACE": "BLACK HISPANIC"
    },
    {
        "count": 4,
        "SUMMONS_DATE": "06/2019",
        "BORO": "BROOKLYN",
        "JURISDICTION_CODE": "0",
        "AGE_GROUP": "45-64",
        "SEX": "M",
        "RACE": "AMERICAN INDIAN/ALASKAN NATIVE"
    },
    {
        "count": 1,
        "SUMMONS_DATE": "06/2019",
        "BORO": "BROOKLYN",
        "JURISDICTION_CODE": "0",
        "AGE_GROUP": "18-24",
        "SEX": "U",
        "RACE": "WHITE"
    },
    {
        "count": 1,
        "SUMMONS_DATE": "06/2019",
        "BORO": "NEW YORK",
        "JURISDICTION_CODE": "2",
        "AGE_GROUP": "25-44",
        "SEX": "F",
        "RACE": "BLACK HISPANIC"
    },
    {
        "count": 1,
        "SUMMONS_DATE": "06/2019",
        "BORO": "NEW YORK",
        "JURISDICTION_CODE": "2",
        "AGE_GROUP": "25-44",
        "SEX": "M",
        "RACE": "WHITE"
    },
    {
        "count": 3,
        "SUMMONS_DATE": "06/2019",
        "BORO": "NEW YORK",
        "JURISDICTION_CODE": "2",
        "AGE_GROUP": "18-24",
        "SEX": "M",
        "RACE": "BLACK HISPANIC"
    },
    {
        "count": 4,
        "SUMMONS_DATE": "06/2019",
        "BORO": "BROOKLYN",
        "JURISDICTION_CODE": "2",
        "AGE_GROUP": "18-24",
        "SEX": "F",
        "RACE": "BLACK"
    },
    {
        "count": 1,
        "SUMMONS_DATE": "06/2019",
        "BORO": "NEW YORK",
        "JURISDICTION_CODE": "0",
        "AGE_GROUP": "25-44",
        "SEX": "F",
        "RACE": "UNKNOWN"
    },
    {
        "count": 3,
        "SUMMONS_DATE": "06/2019",
        "BORO": "BROOKLYN",
        "JURISDICTION_CODE": "2",
        "AGE_GROUP": "18-24",
        "SEX": "M",
        "RACE": "BLACK HISPANIC"
    },
    {
        "count": 5,
        "SUMMONS_DATE": "06/2019",
        "BORO": "BROOKLYN",
        "JURISDICTION_CODE": "0",
        "AGE_GROUP": "25-44",
        "SEX": "F",
        "RACE": "ASIAN / PACIFIC ISLANDER"
    },
    {
        "count": 2,
        "SUMMONS_DATE": "06/2019",
        "BORO": "NEW YORK",
        "JURISDICTION_CODE": "0",
        "AGE_GROUP": "45-64",
        "SEX": "F",
        "RACE": "ASIAN / PACIFIC ISLANDER"
    },
    {
        "count": 2,
        "SUMMONS_DATE": "06/2019",
        "BORO": "STATEN ISLAND",
        "JURISDICTION_CODE": "0",
        "AGE_GROUP": "<18",
        "SEX": "M",
        "RACE": "ASIAN / PACIFIC ISLANDER"
    },
    {
        "count": 1,
        "SUMMONS_DATE": "06/2019",
        "BORO": "BRONX",
        "JURISDICTION_CODE": "0",
        "AGE_GROUP": "65+",
        "SEX": "F",
        "RACE": "WHITE HISPANIC"
    },
    {
        "count": 1,
        "SUMMONS_DATE": "06/2019",
        "BORO": "NEW YORK",
        "JURISDICTION_CODE": "2",
        "AGE_GROUP": "18-24",
        "SEX": "F",
        "RACE": "BLACK"
    },
    {
        "count": 1,
        "SUMMONS_DATE": "06/2019",
        "BORO": "BROOKLYN",
        "JURISDICTION_CODE": "0",
        "AGE_GROUP": "45-64",
        "SEX": "M",
        "RACE": "OTHER"
    },
    {
        "count": 1,
        "SUMMONS_DATE": "06/2019",
        "BORO": "BROOKLYN",
        "JURISDICTION_CODE": "0",
        "AGE_GROUP": "25-44",
        "SEX": "U",
        "RACE": "ASIAN / PACIFIC ISLANDER"
    },
    {
        "count": 2,
        "SUMMONS_DATE": "06/2019",
        "BORO": "BRONX",
        "JURISDICTION_CODE": "0",
        "AGE_GROUP": "UNKNOWN",
        "SEX": "F",
        "RACE": "WHITE HISPANIC"
    },
    {
        "count": 1,
        "SUMMONS_DATE": "06/2019",
        "BORO": "BRONX",
        "JURISDICTION_CODE": "2",
        "AGE_GROUP": "25-44",
        "SEX": "U",
        "RACE": "BLACK HISPANIC"
    },
    {
        "count": 1,
        "SUMMONS_DATE": "06/2019",
        "BORO": "NEW YORK",
        "JURISDICTION_CODE": "0",
        "AGE_GROUP": "18-24",
        "SEX": "F",
        "RACE": "UNKNOWN"
    },
    {
        "count": 1,
        "SUMMONS_DATE": "06/2019",
        "BORO": "BRONX",
        "JURISDICTION_CODE": "0",
        "AGE_GROUP": "18-24",
        "SEX": "U",
        "RACE": "WHITE HISPANIC"
    },
    {
        "count": 3,
        "SUMMONS_DATE": "06/2019",
        "BORO": "NEW YORK",
        "JURISDICTION_CODE": "2",
        "AGE_GROUP": "18-24",
        "SEX": "F",
        "RACE": "WHITE HISPANIC"
    },
    {
        "count": 1,
        "SUMMONS_DATE": "06/2019",
        "BORO": "NEW YORK",
        "JURISDICTION_CODE": "0",
        "AGE_GROUP": "45-64",
        "SEX": "U",
        "RACE": "BLACK HISPANIC"
    },
    {
        "count": 1,
        "SUMMONS_DATE": "06/2019",
        "BORO": "STATEN ISLAND",
        "JURISDICTION_CODE": "0",
        "AGE_GROUP": "45-64",
        "SEX": "M",
        "RACE": "ASIAN / PACIFIC ISLANDER"
    },
    {
        "count": 1,
        "SUMMONS_DATE": "06/2019",
        "BORO": "STATEN ISLAND",
        "JURISDICTION_CODE": "0",
        "AGE_GROUP": "18-24",
        "SEX": "F",
        "RACE": "ASIAN / PACIFIC ISLANDER"
    },
    {
        "count": 1,
        "SUMMONS_DATE": "06/2019",
        "BORO": "BRONX",
        "JURISDICTION_CODE": "1",
        "AGE_GROUP": "25-44",
        "SEX": "M",
        "RACE": "WHITE"
    },
    {
        "count": 4,
        "SUMMONS_DATE": "06/2019",
        "BORO": "QUEENS",
        "JURISDICTION_CODE": "0",
        "AGE_GROUP": "<18",
        "SEX": "M",
        "RACE": "WHITE"
    },
    {
        "count": 1,
        "SUMMONS_DATE": "06/2019",
        "BORO": "NEW YORK",
        "JURISDICTION_CODE": "1",
        "AGE_GROUP": "25-44",
        "SEX": "M",
        "RACE": "BLACK HISPANIC"
    },
    {
        "count": 1,
        "SUMMONS_DATE": "06/2019",
        "BORO": "BRONX",
        "JURISDICTION_CODE": "2",
        "AGE_GROUP": "<18",
        "SEX": "M",
        "RACE": "BLACK HISPANIC"
    },
    {
        "count": 5,
        "SUMMONS_DATE": "06/2019",
        "BORO": "BROOKLYN",
        "JURISDICTION_CODE": "2",
        "AGE_GROUP": "25-44",
        "SEX": "M",
        "RACE": "WHITE HISPANIC"
    },
    {
        "count": 1,
        "SUMMONS_DATE": "06/2019",
        "BORO": "BROOKLYN",
        "JURISDICTION_CODE": "2",
        "AGE_GROUP": "UNKNOWN",
        "SEX": "M",
        "RACE": "BLACK"
    },
    {
        "count": 1,
        "SUMMONS_DATE": "06/2019",
        "BORO": "NEW YORK",
        "JURISDICTION_CODE": "2",
        "AGE_GROUP": "UNKNOWN",
        "SEX": "M",
        "RACE": "BLACK"
    },
    {
        "count": 1,
        "SUMMONS_DATE": "06/2019",
        "BORO": "NEW YORK",
        "JURISDICTION_CODE": "1",
        "AGE_GROUP": "45-64",
        "SEX": "F",
        "RACE": "BLACK"
    },
    {
        "count": 1,
        "SUMMONS_DATE": "06/2019",
        "BORO": "QUEENS",
        "JURISDICTION_CODE": "0",
        "AGE_GROUP": "45-64",
        "SEX": "U",
        "RACE": "UNKNOWN"
    },
    {
        "count": 1,
        "SUMMONS_DATE": "06/2019",
        "BORO": "BRONX",
        "JURISDICTION_CODE": "1",
        "AGE_GROUP": "<18",
        "SEX": "M",
        "RACE": "BLACK"
    },
    {
        "count": 1,
        "SUMMONS_DATE": "06/2019",
        "BORO": "QUEENS",
        "JURISDICTION_CODE": "2",
        "AGE_GROUP": "25-44",
        "SEX": "F",
        "RACE": "BLACK"
    },
    {
        "count": 3,
        "SUMMONS_DATE": "06/2019",
        "BORO": "BRONX",
        "JURISDICTION_CODE": "0",
        "AGE_GROUP": "25-44",
        "SEX": "M",
        "RACE": "UNKNOWN"
    },
    {
        "count": 3,
        "SUMMONS_DATE": "06/2019",
        "BORO": "BRONX",
        "JURISDICTION_CODE": "0",
        "AGE_GROUP": "45-64",
        "SEX": "F",
        "RACE": "BLACK HISPANIC"
    },
    {
        "count": 1,
        "SUMMONS_DATE": "06/2019",
        "BORO": "BRONX",
        "JURISDICTION_CODE": "0",
        "AGE_GROUP": "65+",
        "SEX": "M",
        "RACE": "BLACK HISPANIC"
    },
    {
        "count": 1,
        "SUMMONS_DATE": "06/2019",
        "BORO": "BROOKLYN",
        "JURISDICTION_CODE": "2",
        "AGE_GROUP": "18-24",
        "SEX": "M",
        "RACE": "ASIAN / PACIFIC ISLANDER"
    },
    {
        "count": 2,
        "SUMMONS_DATE": "06/2019",
        "BORO": "NEW YORK",
        "JURISDICTION_CODE": "0",
        "AGE_GROUP": "45-64",
        "SEX": "F",
        "RACE": "BLACK"
    },
    {
        "count": 1,
        "SUMMONS_DATE": "06/2019",
        "BORO": "BRONX",
        "JURISDICTION_CODE": "2",
        "AGE_GROUP": "25-44",
        "SEX": "M",
        "RACE": "ASIAN / PACIFIC ISLANDER"
    },
    {
        "count": 1,
        "SUMMONS_DATE": "06/2019",
        "BORO": "BROOKLYN",
        "JURISDICTION_CODE": "2",
        "AGE_GROUP": "45-64",
        "SEX": "M",
        "RACE": "WHITE"
    },
    {
        "count": 2,
        "SUMMONS_DATE": "06/2019",
        "BORO": "QUEENS",
        "JURISDICTION_CODE": "2",
        "AGE_GROUP": "25-44",
        "SEX": "M",
        "RACE": "BLACK"
    },
    {
        "count": 1,
        "SUMMONS_DATE": "06/2019",
        "BORO": "NEW YORK",
        "JURISDICTION_CODE": "0",
        "AGE_GROUP": "<18",
        "SEX": "M",
        "RACE": "ASIAN / PACIFIC ISLANDER"
    },
    {
        "count": 2,
        "SUMMONS_DATE": "06/2019",
        "BORO": "NEW YORK",
        "JURISDICTION_CODE": "0",
        "AGE_GROUP": "45-64",
        "SEX": "M",
        "RACE": "OTHER"
    },
    {
        "count": 1,
        "SUMMONS_DATE": "06/2019",
        "BORO": "QUEENS",
        "JURISDICTION_CODE": "1",
        "AGE_GROUP": "25-44",
        "SEX": "M",
        "RACE": "WHITE HISPANIC"
    },
    {
        "count": 1,
        "SUMMONS_DATE": "06/2019",
        "BORO": "BROOKLYN",
        "JURISDICTION_CODE": "2",
        "AGE_GROUP": "45-64",
        "SEX": "M",
        "RACE": "BLACK HISPANIC"
    },
    {
        "count": 1,
        "SUMMONS_DATE": "06/2019",
        "BORO": "QUEENS",
        "JURISDICTION_CODE": "0",
        "AGE_GROUP": "25-44",
        "SEX": "F",
        "RACE": "AMERICAN INDIAN/ALASKAN NATIVE"
    },
    {
        "count": 1,
        "SUMMONS_DATE": "06/2019",
        "BORO": "BROOKLYN",
        "JURISDICTION_CODE": "0",
        "AGE_GROUP": "18-24",
        "SEX": "U",
        "RACE": "BLACK"
    },
    {
        "count": 1,
        "SUMMONS_DATE": "06/2019",
        "BORO": "BROOKLYN",
        "JURISDICTION_CODE": "0",
        "AGE_GROUP": "65+",
        "SEX": "F",
        "RACE": "BLACK"
    },
    {
        "count": 1,
        "SUMMONS_DATE": "06/2019",
        "BORO": "STATEN ISLAND",
        "JURISDICTION_CODE": "0",
        "AGE_GROUP": "65+",
        "SEX": "M",
        "RACE": "WHITE"
    },
    {
        "count": 1,
        "SUMMONS_DATE": "06/2019",
        "BORO": "NEW YORK",
        "JURISDICTION_CODE": "0",
        "AGE_GROUP": "25-44",
        "SEX": "U",
        "RACE": "BLACK"
    },
    {
        "count": 2,
        "SUMMONS_DATE": "06/2019",
        "BORO": "STATEN ISLAND",
        "JURISDICTION_CODE": "0",
        "AGE_GROUP": "18-24",
        "SEX": "M",
        "RACE": "BLACK HISPANIC"
    },
    {
        "count": 1,
        "SUMMONS_DATE": "06/2019",
        "BORO": "BROOKLYN",
        "JURISDICTION_CODE": "2",
        "AGE_GROUP": "25-44",
        "SEX": "F",
        "RACE": "WHITE HISPANIC"
    },
    {
        "count": 1,
        "SUMMONS_DATE": "06/2019",
        "BORO": "QUEENS",
        "JURISDICTION_CODE": "0",
        "AGE_GROUP": "65+",
        "SEX": "M",
        "RACE": "WHITE HISPANIC"
    },
    {
        "count": 2,
        "SUMMONS_DATE": "06/2019",
        "BORO": "QUEENS",
        "JURISDICTION_CODE": "0",
        "AGE_GROUP": "<18",
        "SEX": "F",
        "RACE": "BLACK"
    },
    {
        "count": 1,
        "SUMMONS_DATE": "06/2019",
        "BORO": "QUEENS",
        "JURISDICTION_CODE": "2",
        "AGE_GROUP": "25-44",
        "SEX": "M",
        "RACE": "WHITE HISPANIC"
    },
    {
        "count": 1,
        "SUMMONS_DATE": "06/2019",
        "BORO": "QUEENS",
        "JURISDICTION_CODE": "0",
        "AGE_GROUP": "<18",
        "SEX": "M",
        "RACE": "ASIAN / PACIFIC ISLANDER"
    },
    {
        "count": 1,
        "SUMMONS_DATE": "06/2019",
        "BORO": "QUEENS",
        "JURISDICTION_CODE": "1",
        "AGE_GROUP": "25-44",
        "SEX": "M",
        "RACE": "BLACK HISPANIC"
    },
    {
        "count": 1,
        "SUMMONS_DATE": "06/2019",
        "BORO": "BRONX",
        "JURISDICTION_CODE": "2",
        "AGE_GROUP": "45-64",
        "SEX": "U",
        "RACE": "BLACK"
    },
    {
        "count": 1,
        "SUMMONS_DATE": "06/2019",
        "BORO": "NEW YORK",
        "JURISDICTION_CODE": "1",
        "AGE_GROUP": "65+",
        "SEX": "M",
        "RACE": "WHITE HISPANIC"
    },
    {
        "count": 1,
        "SUMMONS_DATE": "06/2019",
        "BORO": "QUEENS",
        "JURISDICTION_CODE": "1",
        "AGE_GROUP": "18-24",
        "SEX": "M",
        "RACE": "WHITE HISPANIC"
    },
    {
        "count": 1,
        "SUMMONS_DATE": "06/2019",
        "BORO": "BRONX",
        "JURISDICTION_CODE": "0",
        "AGE_GROUP": "UNKNOWN",
        "SEX": "M",
        "RACE": "BLACK HISPANIC"
    },
    {
        "count": 1,
        "SUMMONS_DATE": "06/2019",
        "BORO": "QUEENS",
        "JURISDICTION_CODE": "0",
        "AGE_GROUP": "18-24",
        "SEX": "F",
        "RACE": "WHITE"
    },
    {
        "count": 1,
        "SUMMONS_DATE": "06/2019",
        "BORO": "NEW YORK",
        "JURISDICTION_CODE": "1",
        "AGE_GROUP": "18-24",
        "SEX": "F",
        "RACE": "WHITE HISPANIC"
    },
    {
        "count": 2,
        "SUMMONS_DATE": "06/2019",
        "BORO": "NEW YORK",
        "JURISDICTION_CODE": "2",
        "AGE_GROUP": "18-24",
        "SEX": "F",
        "RACE": "BLACK HISPANIC"
    },
    {
        "count": 1,
        "SUMMONS_DATE": "06/2019",
        "BORO": "QUEENS",
        "JURISDICTION_CODE": "0",
        "AGE_GROUP": "25-44",
        "SEX": "M",
        "RACE": "AMERICAN INDIAN/ALASKAN NATIVE"
    },
    {
        "count": 1,
        "SUMMONS_DATE": "06/2019",
        "BORO": "BRONX",
        "JURISDICTION_CODE": "2",
        "AGE_GROUP": "25-44",
        "SEX": "M",
        "RACE": "WHITE"
    },
    {
        "count": 2,
        "SUMMONS_DATE": "06/2019",
        "BORO": "NEW YORK",
        "JURISDICTION_CODE": "1",
        "AGE_GROUP": "45-64",
        "SEX": "M",
        "RACE": "WHITE"
    },
    {
        "count": 1,
        "SUMMONS_DATE": "06/2019",
        "BORO": "BRONX",
        "JURISDICTION_CODE": "2",
        "AGE_GROUP": "45-64",
        "SEX": "F",
        "RACE": "WHITE HISPANIC"
    },
    {
        "count": 4,
        "SUMMONS_DATE": "06/2019",
        "BORO": "NEW YORK",
        "JURISDICTION_CODE": "2",
        "AGE_GROUP": "<18",
        "SEX": "M",
        "RACE": "WHITE"
    },
    {
        "count": 1,
        "SUMMONS_DATE": "06/2019",
        "BORO": "NEW YORK",
        "JURISDICTION_CODE": "2",
        "AGE_GROUP": "<18",
        "SEX": "M",
        "RACE": "ASIAN / PACIFIC ISLANDER"
    },
    {
        "count": 1,
        "SUMMONS_DATE": "06/2019",
        "BORO": "QUEENS",
        "JURISDICTION_CODE": "0",
        "AGE_GROUP": "45-64",
        "SEX": "F",
        "RACE": "UNKNOWN"
    },
    {
        "count": 1,
        "SUMMONS_DATE": "06/2019",
        "BORO": "BROOKLYN",
        "JURISDICTION_CODE": "0",
        "AGE_GROUP": "<18",
        "SEX": "M",
        "RACE": "ASIAN / PACIFIC ISLANDER"
    },
    {
        "count": 2,
        "SUMMONS_DATE": "06/2019",
        "BORO": "BRONX",
        "JURISDICTION_CODE": "2",
        "AGE_GROUP": "UNKNOWN",
        "SEX": "M",
        "RACE": "WHITE HISPANIC"
    },
    {
        "count": 1,
        "SUMMONS_DATE": "06/2019",
        "BORO": "BRONX",
        "JURISDICTION_CODE": "1",
        "AGE_GROUP": "25-44",
        "SEX": "F",
        "RACE": "WHITE"
    },
    {
        "count": 1,
        "SUMMONS_DATE": "06/2019",
        "BORO": "BRONX",
        "JURISDICTION_CODE": "0",
        "AGE_GROUP": "18-24",
        "SEX": "F",
        "RACE": "UNKNOWN"
    },
    {
        "count": 1,
        "SUMMONS_DATE": "06/2019",
        "BORO": "BROOKLYN",
        "JURISDICTION_CODE": "1",
        "AGE_GROUP": "<18",
        "SEX": "M",
        "RACE": "BLACK"
    },
    {
        "count": 1,
        "SUMMONS_DATE": "06/2019",
        "BORO": "BRONX",
        "JURISDICTION_CODE": "1",
        "AGE_GROUP": "45-64",
        "SEX": "F",
        "RACE": "WHITE HISPANIC"
    },
    {
        "count": 1,
        "SUMMONS_DATE": "06/2019",
        "BORO": "BROOKLYN",
        "JURISDICTION_CODE": "1",
        "AGE_GROUP": "18-24",
        "SEX": "F",
        "RACE": "BLACK"
    },
    {
        "count": 1,
        "SUMMONS_DATE": "06/2019",
        "BORO": "NEW YORK",
        "JURISDICTION_CODE": "1",
        "AGE_GROUP": "18-24",
        "SEX": "M",
        "RACE": "BLACK HISPANIC"
    },
    {
        "count": 1,
        "SUMMONS_DATE": "06/2019",
        "BORO": "NEW YORK",
        "JURISDICTION_CODE": "1",
        "AGE_GROUP": "18-24",
        "SEX": "F",
        "RACE": "BLACK"
    },
    {
        "count": 1,
        "SUMMONS_DATE": "06/2019",
        "BORO": "BROOKLYN",
        "JURISDICTION_CODE": "0",
        "AGE_GROUP": "45-64",
        "SEX": "U",
        "RACE": "UNKNOWN"
    },
    {
        "count": 1,
        "SUMMONS_DATE": "06/2019",
        "BORO": "BRONX",
        "JURISDICTION_CODE": "0",
        "AGE_GROUP": "18-24",
        "SEX": "U",
        "RACE": "BLACK"
    },
    {
        "count": 1,
        "SUMMONS_DATE": "06/2019",
        "BORO": "NEW YORK",
        "JURISDICTION_CODE": "1",
        "AGE_GROUP": "25-44",
        "SEX": "M",
        "RACE": "UNKNOWN"
    },
    {
        "count": 1,
        "SUMMONS_DATE": "06/2019",
        "BORO": "BRONX",
        "JURISDICTION_CODE": "1",
        "AGE_GROUP": "65+",
        "SEX": "M",
        "RACE": "ASIAN / PACIFIC ISLANDER"
    },
    {
        "count": 1,
        "SUMMONS_DATE": "06/2019",
        "BORO": "BRONX",
        "JURISDICTION_CODE": "0",
        "AGE_GROUP": "18-24",
        "SEX": "M",
        "RACE": "UNKNOWN"
    },
    {
        "count": 1,
        "SUMMONS_DATE": "06/2019",
        "BORO": "BRONX",
        "JURISDICTION_CODE": "2",
        "AGE_GROUP": "25-44",
        "SEX": "M",
        "RACE": "BLACK HISPANIC"
    }
]